CONTRIBUTING.rst
HISTORY.rst
LICENSE
MANIFEST.in
README.rst
setup.cfg
setup.py
show_qrcode.py
kupfer_plugin_show_qrcode.egg-info/PKG-INFO
kupfer_plugin_show_qrcode.egg-info/SOURCES.txt
kupfer_plugin_show_qrcode.egg-info/dependency_links.txt
kupfer_plugin_show_qrcode.egg-info/not-zip-safe
kupfer_plugin_show_qrcode.egg-info/top_level.txt